{
  "name": "Программист Python",
  "link": "https://spb.hh.ru/vacancy/78926884?from=vacancy_search_list&query=python",
  "salary": "от 70 000 до 100 000 руб. до вычета налогов",
  "company": "РусЭкспресс",
  "address": "Москва"
}{
  "name": "Python разработчик",
  "link": "https://spb.hh.ru/vacancy/79248533?from=vacancy_search_list&query=python",
  "salary": "от 200 000 до 350 000 руб. на руки",
  "company": "Бизнес-Азимут",
  "address": "Москва"
}{
  "name": "Python-разработчик",
  "link": "https://spb.hh.ru/vacancy/79208677?from=vacancy_search_list&query=python",
  "salary": "от 200 000 руб. на руки",
  "company": "ООО ВижнЛабс (VisionLabs)",
  "address": "Москва, Подсосенский переулок, 23с3"
}